OpenFisca_Dummy_Country-0.1.6.dist-info/DESCRIPTION.rst
OpenFisca_Dummy_Country-0.1.6.dist-info/METADATA
OpenFisca_Dummy_Country-0.1.6.dist-info/RECORD
OpenFisca_Dummy_Country-0.1.6.dist-info/WHEEL
OpenFisca_Dummy_Country-0.1.6.dist-info/metadata.json
OpenFisca_Dummy_Country-0.1.6.dist-info/top_level.txt
openfisca_dummy_country/__init__.py
openfisca_dummy_country/__init__.pyc
openfisca_dummy_country/dummy_reform.pyc
openfisca_dummy_country/dummy_reforms.py
openfisca_dummy_country/dummy_reforms.pyc
openfisca_dummy_country/dummy_taxbenefitsystem.py
openfisca_dummy_country/dummy_taxbenefitsystem.pyc
openfisca_dummy_country/entities.py
openfisca_dummy_country/entities.pyc
openfisca_dummy_country/scenarios.py
openfisca_dummy_country/scenarios.pyc
openfisca_dummy_country/dummy_extension/parameters.xml
openfisca_dummy_country/dummy_extension/paris.py
openfisca_dummy_country/dummy_extension/paris.pyc
openfisca_dummy_country/dummy_extension/test.yaml
openfisca_dummy_country/model/model.py
openfisca_dummy_country/model/model.pyc
openfisca_dummy_country/parameters/param_more.xml
openfisca_dummy_country/parameters/param_root.xml
openfisca_dummy_country/tests/failing_test_absolute_error_margin.yaml
openfisca_dummy_country/tests/failing_test_relative_error_margin.yaml
openfisca_dummy_country/tests/test_absolute_error_margin.yaml
openfisca_dummy_country/tests/test_failure.yaml
openfisca_dummy_country/tests/test_name_filter.yaml
openfisca_dummy_country/tests/test_relative_error_margin.yaml
openfisca_dummy_country/tests/test_success.yaml
openfisca_dummy_country/tests/test_with_reform.yaml
openfisca_dummy_country/tests/test_with_reform_2.yaml
openfisca_dummy_country/tests/directory/test_1.yaml
openfisca_dummy_country/tests/directory/test_2.yaml
openfisca_dummy_country/tests/directory/subdirectory/test_4.yaml
