Metadata-Version: 2.0
Name: OpenFisca-Dummy-Country
Version: 0.1.6
Summary: Dummy tax and benefit system used for tests
Home-page: https://github.com/openfisca/openfisca-dummy-country
Author: OpenFisca Team
Author-email: contact@openfisca.fr
License: http://www.fsf.org/licensing/licenses/agpl-3.0.html
Platform: UNKNOWN
Classifier: Development Status :: 2 - Pre-Alpha
Classifier: License :: OSI Approved :: GNU Affero General Public License v3
Classifier: Operating System :: POSIX
Classifier: Programming Language :: Python
Classifier: Topic :: Scientific/Engineering :: Information Analysis
Requires-Dist: OpenFisca-Core (>=12.0.0,<13.0)
